{
  "ts": "2026-03-14T13:02:13.734539+00:00",
  "duration_sec": 60,
  "total": 20929,
  "counts": {
    "app.bsky.feed.like": 13381,
    "app.bsky.graph.follow": 1585,
    "app.bsky.feed.repost": 2192,
    "app.bsky.feed.post": 3254,
    "app.bsky.feed.threadgate": 126,
    "dev.sensorthings.observationBatch": 15,
    "games.gamesgamesgamesgames.game": 15,
    "at.podping.records.podping": 15,
    "app.bsky.graph.block": 104,
    "app.bsky.actor.profile": 65,
    "chat.bsky.actor.declaration": 7,
    "app.bsky.graph.listitem": 23,
    "app.bsky.feed.postgate": 67,
    "host.plural.system.member": 9,
    "app.gainforest.dwc.occurrence": 5,
    "app.bsky.actor.status": 15,
    "fm.teal.alpha.actor.status": 4,
    "place.stream.broadcast.origin": 5,
    "jp.5leaf.sync.mastodon": 2,
    "app.bsky.graph.list": 2,
    "net.mmatt.vitals.car": 1,
    "place.stream.livestream": 4,
    "team.sigint.dm.n": 1,
    "team.sigint.dm.ct": 1,
    "team.sigint.dm.at": 1,
    "social.kibun.status": 1,
    "fm.teal.alpha.feed.play": 2,
    "app.rocksky.song": 1,
    "social.pinksky.app.preference": 1,
    "app.rocksky.album": 1,
    "app.rocksky.scrobble": 1,
    "site.standard.document": 22,
    "app.bsky.labeler.service": 1
  }
}