{
  "ts": "2026-06-05T19:54:44.507941+00:00",
  "duration_sec": 60,
  "total": 23157,
  "counts": {
    "app.bsky.feed.post": 2832,
    "app.bsky.feed.like": 15060,
    "app.bsky.graph.follow": 2141,
    "site.standard.document": 51,
    "app.bsky.feed.repost": 2388,
    "app.bsky.feed.threadgate": 125,
    "link.bridgebeats.lookup": 22,
    "app.rocksky.scrobble": 1,
    "app.bsky.feed.postgate": 82,
    "app.bsky.actor.status": 35,
    "app.bsky.graph.block": 140,
    "app.bsky.actor.profile": 69,
    "tech.transparencia.news.article": 63,
    "store.tz2at.internal.operation": 10,
    "xyz.tz2at.xtz.flow": 4,
    "at.podping.records.podping": 13,
    "store.tz2at.transaction": 3,
    "place.stream.broadcast.origin": 12,
    "app.bsky.graph.listitem": 25,
    "place.stream.livestream": 14,
    "team.sigint.dm.n": 1,
    "id.sifa.profile.skill": 3,
    "team.sigint.dm.ct": 1,
    "chat.bsky.actor.declaration": 5,
    "team.sigint.dm.at": 1,
    "store.tz2at.raw.observation": 5,
    "xyz.tz2at.raw.observation": 3,
    "is.kevara.notifications.readstate": 3,
    "fm.teal.alpha.actor.status": 8,
    "store.tz2at.contract.call": 3,
    "xyz.tz2at.transaction": 3,
    "net.anisota.chronicle.log.daily": 1,
    "fm.teal.alpha.feed.play": 5,
    "net.anisota.chronicle.log.weekly": 1,
    "com.puzzmo.streak": 2,
    "net.anisota.chronicle.log.monthly": 1,
    "store.tz2at.bigmap.update": 1,
    "xyz.tz2at.contract.call": 3,
    "net.anisota.chronicle.expedition": 1,
    "is.kevara.network.snapshot": 1,
    "community.lexicon.sports.baseball.pitcherState": 1,
    "community.lexicon.sports.baseball.gameState": 1,
    "app.didpic.feed.post": 1,
    "store.tz2at.block": 3,
    "social.popfeed.feed.listItem": 2,
    "app.rocksky.song": 1,
    "at.adsb.receiver.sighting": 1,
    "store.tz2at.xtz.flow": 1,
    "place.stream.chat.message": 2,
    "app.didpic.feed.like": 1,
    "id.sifa.profile.position": 1
  }
}