{
  "ts": "2026-06-11T14:36:21.008186+00:00",
  "duration_sec": 60,
  "total": 29343,
  "counts": {
    "app.bsky.feed.like": 19583,
    "app.bsky.feed.repost": 3206,
    "app.bsky.graph.follow": 1767,
    "app.bsky.feed.postgate": 116,
    "app.bsky.feed.post": 3703,
    "app.bsky.graph.block": 224,
    "app.bsky.feed.threadgate": 207,
    "social.mu.newsFeedPrefs": 1,
    "app.bsky.actor.profile": 73,
    "tech.transparencia.news.article": 12,
    "site.standard.document": 16,
    "chat.bsky.actor.declaration": 12,
    "store.tz2at.raw.observation": 7,
    "xyz.tz2at.contract.call": 4,
    "at.podping.records.podping": 16,
    "store.tz2at.xtz.flow": 5,
    "id.sifa.graph.follow": 27,
    "app.bsky.feed.generator": 2,
    "app.bsky.actor.status": 17,
    "net.anisota.chronicle.expedition": 2,
    "fm.teal.alpha.actor.status": 8,
    "place.stream.livestream": 9,
    "app.bsky.labeler.service": 2,
    "store.tz2at.transaction": 6,
    "store.tz2at.contract.call": 5,
    "xyz.tz2at.xtz.flow": 4,
    "fm.teal.alpha.feed.play": 9,
    "app.bsky.notification.declaration": 2,
    "org.hypercerts.claim.activity": 6,
    "app.studynext.task": 95,
    "place.stream.broadcast.origin": 8,
    "app.studynext.record": 1,
    "app.bsky.graph.listitem": 17,
    "app.studynext.settings": 8,
    "xyz.tz2at.raw.observation": 4,
    "link.bridgebeats.lookup": 44,
    "app.userinput.visited": 1,
    "app.rocksky.song": 1,
    "xyz.tz2at.transaction": 4,
    "app.rocksky.scrobble": 1,
    "store.tz2at.account.activity": 9,
    "app.bsky.graph.list": 1,
    "at.noted.radio.play": 1,
    "blue.flashes.feed.post": 1,
    "blue.flashes.photo.exif": 3,
    "app.studynext.tasks": 5,
    "com.puzzmo.streak": 2,
    "app.rocksky.actor.status": 2,
    "app.studynext.plan": 1,
    "team.sigint.dm.n": 1,
    "team.sigint.dm.ct": 1,
    "team.sigint.dm.at": 1,
    "cx.vmx.matadisco": 75,
    "app.userinput.upvote": 1,
    "app.navyfragen.message": 2,
    "at.adsb.aircraft.identity": 1,
    "at.adsb.flight.record": 1
  }
}