{
  "ts": "2025-12-18T12:53:15.590153+00:00",
  "duration_sec": 60,
  "total": 21045,
  "counts": {
    "app.bsky.graph.follow": 2129,
    "app.bsky.feed.repost": 2049,
    "app.bsky.feed.like": 13469,
    "app.bsky.feed.post": 2746,
    "app.bsky.graph.block": 155,
    "app.bsky.actor.profile": 160,
    "app.bsky.graph.listitem": 63,
    "app.bsky.graph.list": 1,
    "app.bsky.feed.threadgate": 120,
    "app.bsky.feed.postgate": 57,
    "fm.teal.alpha.actor.status": 48,
    "social.pinksky.app.preference": 1,
    "app.bsky.notification.declaration": 6,
    "blue.flashes.feed.post": 1,
    "place.stream.broadcast.origin": 6,
    "com.blatball.team": 4,
    "jp.5leaf.sync.mastodon": 8,
    "pet.nkp.uptime.check": 10,
    "sh.weaver.collab.session": 1,
    "app.rocksky.scrobble": 1,
    "chat.bsky.actor.declaration": 1,
    "app.bsky.actor.status": 5,
    "social.popfeed.feed.listItem": 1,
    "team.sigint.dm.n": 1,
    "team.sigint.dm.ct": 1,
    "team.sigint.dm.at": 1
  }
}