{
  "ts": "2026-05-03T22:41:16.901049+00:00",
  "duration_sec": 60,
  "total": 21692,
  "counts": {
    "app.bsky.feed.like": 14101,
    "app.bsky.feed.post": 2520,
    "app.bsky.feed.repost": 2275,
    "app.bsky.graph.follow": 1830,
    "app.bsky.graph.block": 336,
    "app.bsky.feed.threadgate": 127,
    "app.bsky.actor.profile": 50,
    "app.bsky.feed.postgate": 83,
    "site.standard.document": 5,
    "place.stream.live.viewerCount": 14,
    "at.podping.records.podping": 14,
    "chat.bsky.actor.declaration": 13,
    "app.bsky.graph.listitem": 17,
    "place.stream.broadcast.origin": 4,
    "place.stream.livestream": 4,
    "fm.teal.alpha.actor.status": 1,
    "fm.teal.alpha.feed.play": 2,
    "app.bsky.actor.status": 11,
    "app.bsky.graph.listblock": 2,
    "community.lexicon.sports.baseball.pitcherState": 4,
    "community.lexicon.sports.baseball.gameState": 4,
    "com.puzzmo.streak": 1,
    "team.sigint.dm.n": 1,
    "team.sigint.dm.ct": 1,
    "team.sigint.dm.at": 1,
    "link.bridgebeats.lookup": 10,
    "org.hypercerts.claim.activity": 3,
    "cx.vmx.matadisco": 250,
    "at.noted.radio.play": 1,
    "net.anisota.player.state": 1,
    "net.anisota.chronicle.progress": 1,
    "place.stream.key": 1,
    "sh.tangled.actor.profile": 1,
    "community.lexicon.sports.game": 1,
    "dev.dndx.pulse": 1,
    "community.lexicon.sports.baseball.batterState": 1
  }
}