{
  "ts": "2026-02-26T07:06:23.179771+00:00",
  "duration_sec": 60,
  "total": 14152,
  "counts": {
    "app.bsky.feed.like": 9148,
    "app.bsky.feed.repost": 1507,
    "app.bsky.graph.follow": 1217,
    "app.bsky.feed.post": 1748,
    "chat.bsky.actor.declaration": 1,
    "app.bsky.actor.profile": 73,
    "app.bsky.graph.block": 128,
    "app.bsky.graph.listblock": 5,
    "app.bsky.feed.threadgate": 100,
    "at.podping.records.podping": 15,
    "dev.sensorthings.observationBatch": 15,
    "app.bsky.graph.listitem": 43,
    "site.standard.document": 39,
    "app.bsky.feed.postgate": 61,
    "place.stream.broadcast.origin": 15,
    "app.gainforest.dwc.occurrence": 4,
    "blue.flashes.feed.post": 1,
    "app.bsky.actor.status": 9,
    "place.wisp.fs": 1,
    "app.bsky.labeler.service": 1,
    "cx.vmx.dev.tmp001.matadisco": 16,
    "app.bsky.graph.list": 1,
    "team.sigint.dm.n": 1,
    "team.sigint.dm.ct": 1,
    "team.sigint.dm.at": 1,
    "fm.teal.alpha.feed.play": 1
  }
}