{
  "ts": "2026-04-22T22:48:14.756278+00:00",
  "duration_sec": 60,
  "total": 25024,
  "counts": {
    "app.bsky.feed.like": 16876,
    "app.bsky.feed.post": 2706,
    "app.bsky.feed.repost": 2736,
    "app.bsky.graph.follow": 1979,
    "chat.bsky.actor.declaration": 89,
    "app.bsky.graph.block": 165,
    "app.bsky.labeler.service": 4,
    "app.bsky.feed.threadgate": 153,
    "app.bsky.actor.profile": 64,
    "net.anisota.chronicle.expedition": 1,
    "app.bsky.graph.listitem": 71,
    "place.stream.broadcast.origin": 8,
    "app.bsky.feed.postgate": 66,
    "tech.transparencia.news.article": 14,
    "at.podping.records.podping": 14,
    "place.stream.live.viewerCount": 14,
    "app.bsky.actor.status": 17,
    "place.stream.livestream": 8,
    "fm.teal.alpha.actor.status": 1,
    "fm.teal.alpha.feed.play": 2,
    "community.lexicon.sports.baseball.pitcherState": 5,
    "community.lexicon.sports.baseball.gameState": 4,
    "site.standard.document": 7,
    "jp.5leaf.sync.mastodon": 1,
    "app.rocksky.song": 4,
    "app.bsky.graph.list": 4,
    "team.sigint.dm.n": 1,
    "team.sigint.dm.ct": 1,
    "team.sigint.dm.at": 1,
    "net.anisota.player.state": 1,
    "at.noted.radio.play": 1,
    "app.rocksky.artist": 1,
    "app.rocksky.album": 1,
    "community.lexicon.bookmarks.bookmark": 1,
    "com.kipclip.annotation": 1,
    "com.kipclip.tag": 1,
    "app.rocksky.scrobble": 1
  }
}