{
  "ts": "2026-04-27T23:54:21.808493+00:00",
  "duration_sec": 60,
  "total": 21874,
  "counts": {
    "app.bsky.feed.like": 14963,
    "app.bsky.feed.repost": 2510,
    "app.bsky.feed.post": 2478,
    "app.bsky.feed.threadgate": 122,
    "app.bsky.actor.profile": 81,
    "app.bsky.graph.follow": 1269,
    "app.bsky.feed.postgate": 68,
    "app.bsky.graph.listitem": 50,
    "net.anisota.player.state": 4,
    "place.stream.livestream": 13,
    "app.bsky.graph.block": 105,
    "fm.teal.alpha.actor.status": 2,
    "fm.teal.alpha.feed.play": 4,
    "social.popfeed.feed.review": 2,
    "social.popfeed.feed.list": 1,
    "tech.transparencia.news.article": 14,
    "place.stream.live.viewerCount": 14,
    "at.podping.records.podping": 14,
    "site.standard.document": 40,
    "com.puzzmo.streak": 3,
    "place.stream.broadcast.origin": 13,
    "social.popfeed.feed.listItem": 1,
    "place.stream.chat.profile": 1,
    "app.bsky.actor.status": 31,
    "app.bsky.feed.generator": 5,
    "chat.bsky.actor.declaration": 17,
    "link.bridgebeats.lookup": 15,
    "app.rocksky.song": 1,
    "team.sigint.dm.n": 1,
    "app.bsky.notification.declaration": 1,
    "team.sigint.dm.ct": 1,
    "team.sigint.dm.at": 1,
    "place.stream.chat.message": 2,
    "net.anisota.chronicle.expedition": 6,
    "community.lexicon.sports.baseball.pitcherState": 7,
    "community.lexicon.sports.baseball.batterState": 2,
    "community.lexicon.sports.baseball.gameState": 6,
    "app.rocksky.scrobble": 2,
    "app.bsky.labeler.service": 1,
    "blue.tokimeki.sync": 2,
    "app.tomarigi.feed.post": 1
  }
}