{
  "ts": "2026-06-08T20:14:44.945360+00:00",
  "duration_sec": 60,
  "total": 19399,
  "counts": {
    "app.bsky.feed.post": 2172,
    "app.bsky.graph.follow": 1768,
    "app.bsky.feed.repost": 2004,
    "app.bsky.feed.like": 12760,
    "fm.teal.alpha.actor.status": 3,
    "app.bsky.feed.threadgate": 99,
    "app.bsky.graph.block": 209,
    "app.bsky.feed.postgate": 50,
    "place.stream.livestream": 33,
    "app.bsky.actor.profile": 45,
    "site.standard.document": 45,
    "is.currents.feed.save": 17,
    "link.bridgebeats.lookup": 14,
    "store.tz2at.transaction": 3,
    "at.podping.records.podping": 11,
    "xyz.tz2at.contract.call": 3,
    "store.tz2at.contract.call": 5,
    "app.bsky.graph.listitem": 18,
    "chat.bsky.actor.declaration": 11,
    "place.stream.broadcast.origin": 5,
    "org.hypercerts.claim.activity": 3,
    "site.standard.publication": 1,
    "store.tz2at.raw.observation": 3,
    "store.tz2at.account.activity": 10,
    "xyz.tz2at.xtz.flow": 3,
    "cx.vmx.matadisco": 56,
    "fm.teal.alpha.feed.play": 3,
    "app.bsky.actor.status": 17,
    "app.rocksky.song": 3,
    "app.studynext.task": 4,
    "store.tz2at.xtz.flow": 1,
    "xyz.tz2at.raw.observation": 3,
    "com.puzzmo.streak": 2,
    "app.studynext.settings": 1,
    "app.studynext.tasks": 1,
    "at.adsb.flight.record": 3,
    "team.sigint.dm.n": 1,
    "team.sigint.dm.ct": 1,
    "team.sigint.dm.at": 1,
    "xyz.tz2at.transaction": 2,
    "at.adsb.aircraft.identity": 2,
    "buzz.bookhive.book": 1,
    "id.sifa.profile.externalAccount": 1,
    "net.anisota.player.state": 1
  }
}