{
  "ts": "2026-07-09T13:50:07.287753+00:00",
  "duration_sec": 60,
  "total": 25605,
  "counts": {
    "app.bsky.feed.like": 16981,
    "app.bsky.feed.repost": 2634,
    "app.bsky.feed.post": 3288,
    "app.bsky.graph.starterpack": 1,
    "app.bsky.graph.follow": 1875,
    "place.stream.broadcast.origin": 11,
    "site.standard.document": 57,
    "app.studynext.tasks": 3,
    "app.bsky.feed.postgate": 139,
    "app.bsky.graph.block": 117,
    "app.bsky.feed.threadgate": 222,
    "place.stream.livestream": 11,
    "at.adsb.flight.record": 1,
    "app.bsky.graph.listitem": 27,
    "app.bsky.actor.profile": 75,
    "app.bsky.actor.status": 12,
    "at.podping.records.podping": 15,
    "com.nsc.identity.provenData": 15,
    "app.bsky.labeler.service": 1,
    "is.currents.feed.save": 30,
    "fm.teal.alpha.actor.status": 16,
    "fm.teal.alpha.feed.play": 14,
    "app.rocksky.scrobble": 5,
    "app.certified.graph.follow": 1,
    "place.stream.chat.profile": 6,
    "com.puzzmo.streak": 9,
    "dev.cocore.compute.provider": 2,
    "app.rocksky.song": 2,
    "app.studynext.task": 3,
    "team.sigint.dm.n": 1,
    "team.sigint.dm.ct": 1,
    "team.sigint.dm.at": 1,
    "dev.cocore.compute.attestation": 1,
    "place.stream.chat.message": 2,
    "app.studynext.settings": 1,
    "chat.bsky.actor.declaration": 5,
    "app.studynext.plan": 1,
    "app.rocksky.actor.status": 3,
    "jp.5leaf.sync.mastodon": 8,
    "at.noted.radio.play": 2,
    "app.bsky.notification.declaration": 2,
    "app.rocksky.artist": 1,
    "app.didpic.feed.like": 2,
    "app.rocksky.album": 1
  }
}