{
  "ts": "2026-05-10T06:12:45.291010+00:00",
  "duration_sec": 60,
  "total": 13618,
  "counts": {
    "app.bsky.feed.like": 8861,
    "app.bsky.feed.repost": 1459,
    "app.bsky.graph.follow": 1225,
    "app.bsky.feed.post": 1639,
    "app.bsky.actor.profile": 52,
    "app.bsky.feed.threadgate": 95,
    "app.bsky.actor.status": 12,
    "app.bsky.feed.postgate": 63,
    "app.bsky.graph.block": 142,
    "site.standard.document": 17,
    "at.podping.records.podping": 14,
    "place.stream.broadcast.origin": 6,
    "place.stream.livestream": 6,
    "app.bsky.graph.listitem": 10,
    "chat.bsky.actor.declaration": 6,
    "jp.5leaf.sync.mastodon": 1,
    "app.bsky.labeler.service": 1,
    "com.library-sky.bookLog": 1,
    "team.sigint.dm.n": 1,
    "team.sigint.dm.ct": 1,
    "team.sigint.dm.at": 1,
    "app.bsky.graph.listblock": 1,
    "link.bridgebeats.lookup": 2,
    "fm.teal.alpha.feed.play": 1,
    "net.anisota.player.state": 1
  }
}