{
  "ts": "2026-04-29T02:51:28.023855+00:00",
  "duration_sec": 60,
  "total": 17144,
  "counts": {
    "app.bsky.feed.repost": 1739,
    "app.bsky.feed.like": 10635,
    "app.bsky.graph.follow": 1927,
    "app.bsky.feed.post": 2066,
    "app.bsky.feed.threadgate": 122,
    "app.bsky.feed.postgate": 56,
    "app.bsky.graph.block": 98,
    "tech.transparencia.news.article": 14,
    "place.stream.live.viewerCount": 14,
    "at.podping.records.podping": 14,
    "place.stream.livestream": 9,
    "app.bsky.actor.profile": 77,
    "farm.smol.atmos.skyrdle.score": 18,
    "chat.bsky.actor.declaration": 10,
    "place.stream.broadcast.origin": 8,
    "app.bsky.graph.listitem": 11,
    "net.anisota.player.state": 1,
    "site.standard.document": 14,
    "fm.teal.alpha.actor.status": 1,
    "com.puzzmo.streak": 3,
    "cx.vmx.matadisco": 250,
    "app.bsky.actor.status": 21,
    "jp.5leaf.sync.mastodon": 1,
    "app.bsky.graph.list": 1,
    "fyi.atstore.listing.detail": 4,
    "network.cosmik.card": 2,
    "social.popfeed.feed.list": 1,
    "blue.tokimeki.sync": 3,
    "app.rocksky.song": 1,
    "app.bsky.labeler.service": 1,
    "com.whtwnd.blog.entry": 2,
    "community.lexicon.sports.baseball.pitcherState": 2,
    "link.bridgebeats.lookup": 8,
    "community.lexicon.sports.baseball.gameState": 1,
    "team.sigint.dm.n": 1,
    "team.sigint.dm.ct": 1,
    "team.sigint.dm.at": 1,
    "org.hypercerts.claim.activity": 3,
    "network.cosmik.collectionLink": 1,
    "uk.skyblur.post": 1,
    "net.anisota.chronicle.expedition": 1
  }
}