{
  "ts": "2026-02-04T02:28:51.648766+00:00",
  "duration_sec": 60,
  "total": 24181,
  "counts": {
    "app.bsky.feed.like": 15771,
    "app.bsky.feed.repost": 2882,
    "app.bsky.feed.post": 2611,
    "app.bsky.graph.follow": 2126,
    "app.bsky.feed.threadgate": 127,
    "app.bsky.graph.listitem": 245,
    "app.bsky.graph.block": 164,
    "at.podping.records.podping": 15,
    "app.bsky.feed.postgate": 51,
    "app.bsky.actor.status": 19,
    "fm.teal.alpha.actor.status": 3,
    "app.bsky.actor.profile": 92,
    "diy.razorgirl.winter.state": 12,
    "stream.thought.reasoning": 3,
    "place.stream.broadcast.origin": 16,
    "stream.thought.ack": 1,
    "jp.5leaf.sync.mastodon": 1,
    "app.gainforest.dwc.occurrence": 4,
    "diy.razorgirl.winter.thought": 15,
    "network.cosmik.collection": 1,
    "network.cosmik.card": 1,
    "network.cosmik.collectionLink": 1,
    "diy.razorgirl.winter.fact": 1,
    "app.bsky.graph.listblock": 1,
    "team.sigint.dm.n": 1,
    "team.sigint.dm.ct": 1,
    "team.sigint.dm.at": 1,
    "app.rocksky.scrobble": 2,
    "social.popfeed.challenge.participation": 1,
    "stream.thought.tool.call": 2,
    "fm.teal.alpha.feed.play": 2,
    "com.blatball.team": 4,
    "place.stream.chat.gate": 1,
    "app.bsky.graph.starterpack": 1,
    "app.bsky.labeler.service": 1,
    "app.rocksky.song": 1
  }
}