{
  "ts": "2026-07-10T14:25:18.902190+00:00",
  "duration_sec": 60,
  "total": 19595,
  "counts": {
    "app.bsky.feed.like": 12676,
    "app.bsky.graph.follow": 1597,
    "app.bsky.feed.repost": 2096,
    "app.bsky.feed.post": 2618,
    "app.bsky.feed.threadgate": 140,
    "app.bsky.graph.block": 108,
    "place.stream.broadcast.origin": 8,
    "app.bsky.feed.postgate": 74,
    "place.stream.chat.profile": 5,
    "app.bsky.graph.listitem": 34,
    "jp.5leaf.sync.mastodon": 6,
    "app.bsky.actor.profile": 82,
    "app.studynext.tasks": 2,
    "team.sigint.dm.n": 1,
    "chat.bsky.actor.declaration": 11,
    "app.rocksky.actor.status": 8,
    "is.currents.feed.save": 20,
    "fm.teal.alpha.feed.play": 7,
    "place.stream.chat.message": 5,
    "fm.teal.alpha.actor.status": 10,
    "app.bsky.actor.status": 15,
    "site.standard.document": 33,
    "at.podping.records.podping": 4,
    "app.studynext.task": 5,
    "dev.cocore.compute.provider": 2,
    "app.greengale.document": 1,
    "net.anisota.chronicle.expedition": 1,
    "dev.cocore.compute.attestation": 1,
    "app.rocksky.song": 4,
    "app.rocksky.artist": 2,
    "at.adsb.flight.record": 1,
    "app.rocksky.album": 2,
    "app.rocksky.scrobble": 4,
    "place.stream.livestream": 6,
    "app.studynext.settings": 1,
    "app.bsky.labeler.service": 1,
    "place.stream.key": 1,
    "ing.dasl.masl": 1,
    "pub.mini.deployment": 1,
    "pub.mini.site": 1
  }
}