{
  "ts": "2026-07-20T06:22:17.646947+00:00",
  "duration_sec": 60,
  "total": 14624,
  "counts": {
    "app.bsky.feed.like": 9683,
    "app.bsky.graph.block": 82,
    "app.bsky.feed.post": 2055,
    "app.bsky.graph.follow": 733,
    "app.bsky.feed.repost": 1391,
    "app.bsky.actor.profile": 49,
    "app.studynext.task": 33,
    "app.bsky.feed.threadgate": 115,
    "app.bsky.feed.postgate": 64,
    "app.bsky.actor.status": 17,
    "community.lexicon.bookmarks.bookmark": 1,
    "com.kipclip.annotation": 1,
    "site.standard.document": 31,
    "app.bsky.graph.listitem": 28,
    "dev.sensorthings.observationBatch": 113,
    "at.podping.records.podping": 14,
    "app.studynext.tasks": 5,
    "place.stream.broadcast.origin": 10,
    "app.studynext.status": 6,
    "is.dame.arena.mirror.channel": 7,
    "is.dame.arena.mirror.block": 134,
    "is.dame.arena.mirror.connection": 17,
    "app.bsky.notification.declaration": 1,
    "app.rocksky.actor.status": 1,
    "app.certified.actor.profile": 1,
    "place.stream.livestream": 10,
    "fm.teal.alpha.feed.play": 2,
    "chat.bsky.actor.declaration": 4,
    "fm.teal.alpha.actor.status": 2,
    "app.studynext.record": 1,
    "app.rocksky.scrobble": 1,
    "app.studynext.plan": 1,
    "app.bsky.labeler.service": 1,
    "is.dame.arena.mirror.sync": 1,
    "blue.flashes.feed.post": 1,
    "social.coves.community.post": 1,
    "app.bsky.graph.list": 1,
    "team.sigint.dm.n": 1,
    "team.sigint.dm.ct": 1,
    "team.sigint.dm.at": 1,
    "wtf.cee.topchicken.execution": 1,
    "app.bsky.graph.starterpack": 1,
    "app.studynext.backup": 1
  }
}