{
  "ts": "2026-07-22T19:17:26.098332+00:00",
  "duration_sec": 60,
  "total": 21236,
  "counts": {
    "app.bsky.feed.like": 14180,
    "app.bsky.feed.post": 2677,
    "app.bsky.feed.repost": 2283,
    "app.bsky.graph.block": 153,
    "app.bsky.graph.listitem": 27,
    "app.bsky.graph.follow": 1355,
    "app.qte.coin.wallet": 135,
    "app.bsky.notification.declaration": 1,
    "app.bsky.actor.profile": 65,
    "app.bsky.actor.status": 16,
    "social.coves.community.post": 6,
    "app.bsky.graph.list": 1,
    "app.bsky.feed.threadgate": 119,
    "app.bsky.feed.postgate": 71,
    "net.anisota.player.state": 6,
    "at.podping.records.podping": 12,
    "dev.sensorthings.observationBatch": 33,
    "fm.teal.alpha.feed.play": 6,
    "fm.teal.alpha.actor.status": 6,
    "at.adsb.flight.record": 4,
    "site.standard.document": 24,
    "app.studynext.tasks": 1,
    "place.stream.livestream": 7,
    "place.stream.broadcast.origin": 7,
    "app.studynext.task": 4,
    "link.bridgebeats.lookup": 7,
    "community.lexicon.sports.baseball.pitcherState": 4,
    "community.lexicon.sports.baseball.gameState": 2,
    "dev.cocore.compute.provider": 4,
    "dev.cocore.compute.attestation": 2,
    "community.blacksky.feed.post": 1,
    "app.rocksky.scrobble": 3,
    "app.rocksky.actor.status": 2,
    "at.adsb.receiver.sighting": 1,
    "app.rocksky.song": 1,
    "sh.tangled.repo": 1,
    "wtf.cee.topchicken.execution": 2,
    "net.anisota.chronicle.collection": 2,
    "net.anisota.chronicle.log": 1,
    "net.anisota.chronicle.log.daily": 2,
    "net.anisota.chronicle.progress": 1,
    "app.bsky.labeler.service": 1
  }
}