{
  "ts": "2025-12-18T18:38:27.505999+00:00",
  "duration_sec": 60,
  "total": 25873,
  "counts": {
    "app.bsky.graph.follow": 1748,
    "app.bsky.feed.post": 3083,
    "app.bsky.feed.like": 17306,
    "app.bsky.feed.repost": 2934,
    "app.bsky.graph.block": 434,
    "app.bsky.actor.profile": 89,
    "fm.teal.alpha.actor.status": 43,
    "chat.bsky.actor.declaration": 1,
    "app.bsky.feed.threadgate": 114,
    "app.bsky.feed.postgate": 55,
    "app.bsky.actor.status": 6,
    "app.bsky.graph.listitem": 25,
    "app.bsky.graph.starterpack": 2,
    "app.bsky.notification.declaration": 1,
    "app.bsky.graph.list": 1,
    "com.blatball.team": 4,
    "place.stream.broadcast.origin": 6,
    "pet.nkp.uptime.check": 10,
    "net.anisota.beta.game.session": 1,
    "net.anisota.beta.game.log": 3,
    "team.sigint.dm.n": 1,
    "team.sigint.dm.ct": 1,
    "team.sigint.dm.at": 1,
    "app.bsky.labeler.service": 2,
    "jp.5leaf.sync.mastodon": 1,
    "fm.teal.alpha.feed.play": 1
  }
}