{
  "ts": "2026-04-18T08:51:43.587866+00:00",
  "duration_sec": 60,
  "total": 13307,
  "counts": {
    "app.bsky.feed.like": 8238,
    "app.bsky.feed.post": 2102,
    "app.bsky.feed.repost": 1334,
    "app.bsky.graph.block": 147,
    "app.bsky.graph.follow": 919,
    "app.rocksky.artist": 1,
    "app.rocksky.album": 1,
    "app.bsky.feed.threadgate": 74,
    "place.stream.live.viewerCount": 15,
    "tech.transparencia.news.article": 15,
    "at.podping.records.podping": 15,
    "cx.vmx.matadisco": 250,
    "site.standard.document": 10,
    "app.bsky.actor.profile": 60,
    "app.bsky.feed.postgate": 56,
    "fm.teal.alpha.feed.play": 9,
    "app.bsky.graph.listitem": 11,
    "link.bridgebeats.lookup": 4,
    "app.rocksky.scrobble": 2,
    "net.anisota.chronicle.expedition": 2,
    "fm.teal.alpha.actor.status": 4,
    "place.stream.broadcast.origin": 12,
    "app.bsky.actor.status": 8,
    "place.stream.livestream": 12,
    "me.linkna.lastfm": 1,
    "com.puzzmo.streak": 2,
    "team.sigint.dm.n": 1,
    "team.sigint.dm.ct": 1,
    "team.sigint.dm.at": 1
  }
}