{
  "ts": "2026-04-12T15:36:30.440912+00:00",
  "duration_sec": 60,
  "total": 28152,
  "counts": {
    "app.bsky.feed.post": 3189,
    "app.bsky.feed.postgate": 89,
    "app.bsky.feed.like": 18786,
    "app.bsky.feed.repost": 3110,
    "app.bsky.graph.follow": 2008,
    "app.bsky.graph.block": 194,
    "app.bsky.feed.threadgate": 166,
    "app.bsky.actor.status": 16,
    "app.bsky.actor.profile": 108,
    "place.stream.live.viewerCount": 93,
    "fm.teal.alpha.feed.play": 5,
    "at.podping.records.podping": 14,
    "tech.transparencia.news.article": 1,
    "net.anisota.chronicle.expedition": 2,
    "app.bsky.graph.listitem": 36,
    "fm.teal.alpha.actor.status": 3,
    "tech.transparencia.news.source": 13,
    "place.stream.broadcast.origin": 12,
    "app.bsky.feed.generator": 1,
    "app.bsky.labeler.service": 5,
    "app.bsky.graph.list": 3,
    "place.stream.livestream": 12,
    "link.bridgebeats.lookup": 6,
    "app.bluefeed.feed.generator": 1,
    "team.sigint.dm.n": 1,
    "team.sigint.dm.ct": 1,
    "team.sigint.dm.at": 1,
    "site.standard.document": 7,
    "cx.vmx.matadisco": 250,
    "chat.bsky.actor.declaration": 1,
    "io.atcr.hold.scan": 2,
    "app.rocksky.song": 1,
    "app.rocksky.artist": 1,
    "app.rocksky.album": 1,
    "com.puzzmo.streak": 2,
    "app.rocksky.scrobble": 1,
    "site.standard.publication": 1,
    "blog.pckt.publication": 1,
    "net.anisota.chronicle.log.daily": 1,
    "net.anisota.chronicle.log.weekly": 1,
    "net.anisota.chronicle.log.monthly": 1,
    "net.anisota.chronicle.log.yearly": 1,
    "net.anisota.player.state": 2,
    "tech.manos.twmirror.post": 1,
    "org.hypercerts.claim.activity": 1
  }
}