{
  "ts": "2026-05-16T05:55:14.000209+00:00",
  "duration_sec": 60,
  "total": 14085,
  "counts": {
    "app.bsky.feed.like": 9412,
    "app.bsky.feed.repost": 1546,
    "app.bsky.feed.post": 1701,
    "app.ch.poltr.review.invitation": 15,
    "app.bsky.feed.postgate": 59,
    "at.podping.records.podping": 15,
    "app.bsky.feed.threadgate": 114,
    "app.bsky.graph.follow": 1026,
    "app.bsky.graph.block": 93,
    "app.bsky.graph.listitem": 18,
    "place.stream.broadcast.origin": 4,
    "place.stream.livestream": 4,
    "app.bsky.actor.profile": 47,
    "dev.chrispardy.atrand.rfe": 1,
    "com.zorsky.turn": 1,
    "net.anisota.chronicle.expedition": 2,
    "net.anisota.player.state": 1,
    "chat.bsky.actor.declaration": 4,
    "site.standard.document": 3,
    "app.bsky.labeler.service": 1,
    "app.bsky.actor.status": 10,
    "fm.teal.alpha.feed.play": 1,
    "fm.teal.alpha.actor.status": 1,
    "app.bsky.graph.list": 1,
    "team.sigint.dm.n": 1,
    "team.sigint.dm.ct": 1,
    "team.sigint.dm.at": 1,
    "com.getorbyt.profile": 2
  }
}