{
  "ts": "2026-05-19T00:06:20.302564+00:00",
  "duration_sec": 60,
  "total": 1716,
  "counts": {
    "app.bsky.feed.repost": 216,
    "app.bsky.feed.like": 1036,
    "app.bsky.graph.follow": 126,
    "app.bsky.feed.post": 246,
    "at.podping.records.podping": 15,
    "place.stream.livestream": 2,
    "app.bsky.graph.block": 12,
    "place.stream.broadcast.origin": 2,
    "site.standard.document": 6,
    "app.bsky.feed.postgate": 8,
    "app.bsky.graph.listitem": 9,
    "app.bsky.actor.profile": 8,
    "eco.astrosky.transient.gcn": 1,
    "io.bskyrad.play": 1,
    "io.bskyrad.banter": 1,
    "io.bskyrad.nowPlaying": 1,
    "app.bsky.feed.threadgate": 11,
    "link.bridgebeats.lookup": 8,
    "app.bsky.actor.status": 2,
    "fm.teal.alpha.actor.status": 1,
    "fm.teal.alpha.feed.play": 2,
    "app.certified.location": 1,
    "org.hypercerts.claim.activity": 1
  }
}