{
  "ts": "2026-06-06T17:14:15.501070+00:00",
  "duration_sec": 60,
  "total": 23706,
  "counts": {
    "app.bsky.feed.like": 15934,
    "app.bsky.feed.post": 2889,
    "app.bsky.feed.repost": 2525,
    "app.bsky.graph.follow": 1489,
    "app.bsky.graph.block": 260,
    "app.bsky.actor.profile": 86,
    "at.podping.records.podping": 16,
    "store.tz2at.index.ref": 21,
    "xyz.tz2at.contract.call": 4,
    "store.tz2at.transaction": 4,
    "app.bsky.feed.threadgate": 149,
    "app.bsky.feed.postgate": 87,
    "com.puzzmo.streak": 6,
    "app.bsky.actor.status": 33,
    "app.bsky.graph.listitem": 33,
    "chat.bsky.actor.declaration": 13,
    "site.standard.document": 15,
    "place.stream.broadcast.origin": 14,
    "app.bsky.graph.list": 3,
    "net.anisota.player.state": 3,
    "uk.skyblur.post": 1,
    "store.tz2at.contract.call": 4,
    "xyz.tz2at.xtz.flow": 4,
    "fm.teal.alpha.actor.status": 7,
    "fm.teal.alpha.feed.play": 8,
    "net.anisota.chronicle.expedition": 4,
    "store.tz2at.raw.observation": 7,
    "xyz.tz2at.raw.observation": 4,
    "place.stream.livestream": 14,
    "app.studynext.task": 17,
    "app.studynext.settings": 5,
    "app.rocksky.song": 3,
    "app.rocksky.artist": 1,
    "xyz.tz2at.transaction": 4,
    "app.rocksky.album": 3,
    "app.rocksky.scrobble": 4,
    "com.denazen.messagingkeys": 1,
    "com.denazen.headentrykey": 1,
    "com.denazen.friendidentities": 1,
    "com.denazen.circleheads": 1,
    "at.noted.radio.play": 1,
    "store.tz2at.bigmap.update": 1,
    "app.bsky.labeler.service": 1,
    "team.sigint.dm.n": 1,
    "team.sigint.dm.ct": 1,
    "team.sigint.dm.at": 1,
    "app.studynext.tasks": 2,
    "community.lexicon.sports.baseball.pitcherState": 2,
    "community.lexicon.sports.baseball.gameState": 2,
    "store.tz2at.marketplace.collect": 2,
    "link.bridgebeats.lookup": 4,
    "at.adsb.receiver.sighting": 1,
    "store.tz2at.fa2.transfer": 1,
    "store.tz2at.account.activity": 3,
    "at.adsb.aircraft.identity": 1,
    "at.adsb.flight.record": 2,
    "store.tz2at.internal.operation": 1,
    "sh.tangled.feed.reaction": 1
  }
}