{
  "ts": "2026-07-03T19:21:30.146712+00:00",
  "duration_sec": 60,
  "total": 19558,
  "counts": {
    "app.bsky.graph.follow": 2161,
    "app.bsky.feed.repost": 1912,
    "app.bsky.feed.like": 12135,
    "app.bsky.feed.post": 2695,
    "app.bsky.actor.status": 35,
    "app.bsky.graph.listitem": 63,
    "app.bsky.feed.postgate": 74,
    "link.bridgebeats.lookup": 5,
    "app.bsky.actor.profile": 56,
    "app.bsky.graph.block": 127,
    "store.tz2at.index.ref": 48,
    "app.bsky.feed.threadgate": 125,
    "com.puzzmo.streak": 2,
    "place.stream.broadcast.origin": 14,
    "store.tz2at.raw.observation": 1,
    "place.stream.chat.message": 5,
    "at.podping.records.podping": 14,
    "fm.teal.alpha.feed.play": 5,
    "fm.teal.alpha.actor.status": 9,
    "place.stream.livestream": 14,
    "app.rocksky.scrobble": 7,
    "site.standard.document": 10,
    "store.tz2at.bigmap.update": 4,
    "app.rocksky.song": 8,
    "app.rocksky.artist": 1,
    "chat.bsky.actor.declaration": 8,
    "app.rocksky.album": 1,
    "dev.npmx.actor.profile": 1,
    "org.lichess.puzzle.attempt": 2,
    "so.sprk.feed.post": 1,
    "sh.tangled.feed.comment": 1,
    "sh.tangled.repo.issue.state": 1,
    "dev.npmx.feed.like": 1,
    "xyz.opnshelf.episode": 1,
    "store.tz2at.transaction": 1,
    "at.noted.radio.play": 1,
    "app.bsky.graph.list": 2,
    "blog.pckt.mini.post": 1,
    "store.tz2at.xtz.flow": 1,
    "blog.pckt.mini.repost": 1,
    "io.atcr.hold.stats": 1,
    "io.atcr.hold.stats.daily": 1,
    "store.tz2at.contract.call": 1,
    "pics.atmo.image": 1
  }
}