{
  "ts": "2026-05-21T22:18:56.900189+00:00",
  "duration_sec": 60,
  "total": 25759,
  "counts": {
    "app.bsky.graph.follow": 1792,
    "app.bsky.feed.like": 16825,
    "app.bsky.graph.block": 1370,
    "app.bsky.feed.post": 2588,
    "app.bsky.feed.repost": 2745,
    "site.standard.document": 18,
    "fm.teal.alpha.feed.play": 23,
    "app.bsky.feed.threadgate": 130,
    "app.bsky.feed.postgate": 58,
    "fm.teal.alpha.actor.status": 21,
    "at.podping.records.podping": 15,
    "chat.bsky.actor.declaration": 8,
    "app.rocksky.scrobble": 21,
    "place.stream.broadcast.origin": 6,
    "app.bsky.actor.profile": 53,
    "app.bsky.graph.listitem": 33,
    "com.puzzmo.streak": 3,
    "app.rocksky.song": 1,
    "sh.tangled.spindle.member": 1,
    "sh.tangled.knot.member": 1,
    "sh.tangled.actor.profile": 1,
    "blue.flashes.feed.post": 1,
    "app.bsky.actor.status": 21,
    "place.stream.chat.profile": 1,
    "place.stream.livestream": 4,
    "link.bridgebeats.lookup": 8,
    "ai.afrilingua.actor.encryptionKey": 2,
    "community.lexicon.sports.baseball.pitcherState": 2,
    "community.lexicon.sports.baseball.gameState": 1,
    "team.sigint.dm.n": 1,
    "team.sigint.dm.ct": 1,
    "net.anisota.player.state": 1,
    "team.sigint.dm.at": 1,
    "app.bsky.notification.declaration": 1,
    "link.woosh.linkPage": 1
  }
}