{
  "ts": "2025-12-16T06:40:18.210257+00:00",
  "duration_sec": 60,
  "total": 15019,
  "counts": {
    "app.bsky.feed.like": 9370,
    "app.bsky.feed.repost": 1436,
    "app.bsky.graph.follow": 1822,
    "app.bsky.feed.post": 1983,
    "fm.teal.alpha.actor.status": 47,
    "app.bsky.feed.threadgate": 81,
    "app.bsky.graph.block": 155,
    "app.bsky.actor.profile": 51,
    "app.bsky.feed.postgate": 36,
    "place.stream.broadcast.origin": 4,
    "app.bsky.graph.listitem": 15,
    "fm.teal.alpha.feed.play": 6,
    "app.bsky.feed.generator": 2,
    "app.bsky.actor.status": 6,
    "chat.bsky.actor.declaration": 1,
    "com.blatball.team": 4
  }
}